mypackage/__init__.py
mypackage/app.py
cv2_brightness-0.0.1.dist-info/LICENSE
cv2_brightness-0.0.1.dist-info/METADATA
cv2_brightness-0.0.1.dist-info/WHEEL
cv2_brightness-0.0.1.dist-info/top_level.txt
cv2_brightness-0.0.1.dist-info/RECORD
