Metadata-Version: 2.1
Name: cv2-brightness
Version: 0.0.1
Summary: this package for control your pc brightness using your right hand
Home-page: https://github.com/pypa/sampleproject
Author: ZaidAlwawi
Author-email: zaidwawi@gmail.com
Project-URL: Bug Tracker, https://github.com/pypa/sampleproject/issues
Classifier: Programming Language :: Python :: 3
Classifier: License :: OSI Approved :: MIT License
Classifier: Operating System :: OS Independent
Requires-Python: >=3.6
License-File: LICENSE
